{
    "page": 3,
    "more": false,
    "results": [
        {
            "id": "21",
            "title": "This is one line title example",
            "description": "On Nov. 9, 2002, Kentucky celebrates prematurely, and some more text goes after…",
            "read": true,
            "event": "prize_won",
            "message": {
                "data": {
                    "event": "prize_won"
                },
                "notification": {
                    "body": "Tap here to redeem your [prize_name]",
                    "title": "You won a prize!"
                }
            },
            "date_created": "2020-02-04T12:58:51.234Z"
        },
        {
            "id": "22",
            "title": "This is one line title example",
            "description": "On Nov. 9, 2002, Kentucky celebrates prematurely, and some more text goes after…",
            "read": true,
            "event": "prize_won",
            "message": {
                "data": {
                    "event": "prize_won"
                },
                "notification": {
                    "body": "Tap here to redeem your [prize_name]",
                    "title": "You won a prize!"
                }
            },
            "date_created": "2020-02-04T12:58:51.234Z"
        },
        {
            "id": "23",
            "title": "This is one line title example",
            "description": "On Nov. 9, 2002, Kentucky celebrates prematurely, and some more text goes after…",
            "read": true,
            "event": "prize_won",
            "message": {
                "data": {
                    "event": "prize_won"
                },
                "notification": {
                    "body": "Tap here to redeem your [prize_name]",
                    "title": "You won a prize!"
                }
            },
            "date_created": "2020-02-04T12:58:51.234Z"
        },
        {
            "id": "24",
            "title": "This is one line title example",
            "description": "On Nov. 9, 2002, Kentucky celebrates prematurely, and some more text goes after…",
            "read": true,
            "event": "prize_won",
            "message": {
                "data": {
                    "event": "prize_won"
                },
                "notification": {
                    "body": "Tap here to redeem your [prize_name]",
                    "title": "You won a prize!"
                }
            },
            "date_created": "2020-02-04T12:58:51.234Z"
        },
        {
            "id": "25",
            "title": "This is one line title example",
            "description": "On Nov. 9, 2002, Kentucky celebrates prematurely, and some more text goes after…",
            "read": true,
            "event": "prize_won",
            "message": {
                "data": {
                    "event": "prize_won"
                },
                "notification": {
                    "body": "Tap here to redeem your [prize_name]",
                    "title": "You won a prize!"
                }
            },
            "date_created": "2020-02-04T12:58:51.234Z"
        },
        {
            "id": "26",
            "title": "This is one line title example",
            "description": "On Nov. 9, 2002, Kentucky celebrates prematurely, and some more text goes after…",
            "read": true,
            "event": "prize_won",
            "message": {
                "data": {
                    "event": "prize_won"
                },
                "notification": {
                    "body": "Tap here to redeem your [prize_name]",
                    "title": "You won a prize!"
                }
            },
            "date_created": "2020-02-04T12:58:51.234Z"
        },
        {
            "id": "27",
            "title": "This is one line title example",
            "description": "On Nov. 9, 2002, Kentucky celebrates prematurely, and some more text goes after…",
            "read": true,
            "event": "prize_won",
            "message": {
                "data": {
                    "event": "prize_won"
                },
                "notification": {
                    "body": "Tap here to redeem your [prize_name]",
                    "title": "You won a prize!"
                }
            },
            "date_created": "2020-02-04T12:58:51.234Z"
        },
        {
            "id": "28",
            "title": "This is one line title example",
            "description": "On Nov. 9, 2002, Kentucky celebrates prematurely, and some more text goes after…",
            "read": true,
            "event": "prize_won",
            "message": {
                "data": {
                    "event": "prize_won"
                },
                "notification": {
                    "body": "Tap here to redeem your [prize_name]",
                    "title": "You won a prize!"
                }
            },
            "date_created": "2020-02-04T12:58:51.234Z"
        },
        {
            "id": "29",
            "title": "This is one line title example",
            "description": "On Nov. 9, 2002, Kentucky celebrates prematurely, and some more text goes after…",
            "read": true,
            "event": "prize_won",
            "message": {
                "data": {
                    "event": "prize_won"
                },
                "notification": {
                    "body": "Tap here to redeem your [prize_name]",
                    "title": "You won a prize!"
                }
            },
            "date_created": "2020-02-04T12:58:51.234Z"
        },
        {
            "id": "30",
            "title": "This is one line title example",
            "description": "On Nov. 9, 2002, Kentucky celebrates prematurely, and some more text goes after…",
            "read": true,
            "event": "prize_won",
            "message": {
                "data": {
                    "event": "prize_won"
                },
                "notification": {
                    "body": "Tap here to redeem your [prize_name]",
                    "title": "You won a prize!"
                }
            },
            "date_created": "2020-02-04T12:58:51.234Z"
        }
    ]
}